tictactoe/__init__.py
tictactoe/ai.py
tictactoe/board.py
tictactoe/cli.py
tictactoe_vish-0.1.0.dist-info/licenses/LICENSE
tictactoe_vish-0.1.0.dist-info/METADATA
tictactoe_vish-0.1.0.dist-info/WHEEL
tictactoe_vish-0.1.0.dist-info/entry_points.txt
tictactoe_vish-0.1.0.dist-info/top_level.txt
tictactoe_vish-0.1.0.dist-info/RECORD
