Metadata-Version: 2.4
Name: tictactoe-vish
Version: 0.1.0
Summary: A modern, well-tested Tic-Tac-Toe game implementation in Python with CLI interface and AI opponent
Author-email: Vishwas <your.email@example.com>
Maintainer-email: Vishwas <your.email@example.com>
License: MIT
Project-URL: Homepage, https://github.com/v-s-v-i-s-h-w-a-s/tic-tac-toe
Project-URL: Repository, https://github.com/v-s-v-i-s-h-w-a-s/tic-tac-toe
Project-URL: Issues, https://github.com/v-s-v-i-s-h-w-a-s/tic-tac-toe/issues
Project-URL: Changelog, https://github.com/v-s-v-i-s-h-w-a-s/tic-tac-toe/releases
Keywords: game,tic-tac-toe,ai,minimax,cli
Classifier: Development Status :: 4 - Beta
Classifier: Intended Audience :: End Users/Desktop
Classifier: License :: OSI Approved :: MIT License
Classifier: Operating System :: OS Independent
Classifier: Programming Language :: Python :: 3
Classifier: Programming Language :: Python :: 3.8
Classifier: Programming Language :: Python :: 3.9
Classifier: Programming Language :: Python :: 3.10
Classifier: Programming Language :: Python :: 3.11
Classifier: Programming Language :: Python :: 3.12
Classifier: Topic :: Games/Entertainment :: Board Games
Classifier: Topic :: Software Development :: Libraries :: Python Modules
Requires-Python: >=3.8
License-File: LICENSE
Provides-Extra: dev
Requires-Dist: pytest>=7.0; extra == "dev"
Requires-Dist: pytest-cov>=4.0; extra == "dev"
Requires-Dist: black>=23.0; extra == "dev"
Requires-Dist: flake8>=6.0; extra == "dev"
Requires-Dist: isort>=5.0; extra == "dev"
Requires-Dist: pylint>=2.15; extra == "dev"
Dynamic: license-file
